{
  "timestamp": "2026-07-24T07:50:40.848097+09:00",
  "label": "07:50",
  "items": [
    {
      "keyword": "2026",
      "traffic_raw": "1000+",
      "traffic": 1000,
      "news": {
        "title": "2026 National Educators Rising National Conference Competition",
        "source": "Richardson ISD",
        "url": "https://web.risd.org/home/2026-national-educators-rising-national-conference-competition/"
      }
    },
    {
      "keyword": "빌라",
      "traffic_raw": "1000+",
      "traffic": 1000,
      "news": {
        "title": "주차·방음에 보증금 보호까지 '사각지대'…비아파트가 외면받는 이유 [주거사다리의 '밑단'·③]",
        "source": "Daum",
        "url": "https://v.daum.net/v/20260724070129147"
      }
    },
    {
      "keyword": "tsla",
      "traffic_raw": "1000+",
      "traffic": 1000,
      "news": {
        "title": "Tesla's profitability deteriorated in the second quarter of this year due to its performance far bel..",
        "source": "매일경제",
        "url": "https://www.mk.co.kr/en/it/12105049"
      }
    },
    {
      "keyword": "vix",
      "traffic_raw": "500+",
      "traffic": 500,
      "news": {
        "title": "India VIX Closes Up 1.35% at 13.47 as Geopolitical Risks and Crude Oil Keep Volatility Elevated",
        "source": "HDFC Sky",
        "url": "https://hdfcsky.com/news/india-vix-ends-at-13-47-as-volatility-persists"
      }
    },
    {
      "keyword": "케이리 호틀",
      "traffic_raw": "200+",
      "traffic": 200,
      "news": {
        "title": "'고질라' 18세 지아, 사망 직전 참혹했던 녹취록 공개 \"수어 통역 시급\" [Oh!llywood]",
        "source": "OSEN",
        "url": "http://www.osen.co.kr/article/G1112844169"
      }
    },
    {
      "keyword": "tqqq",
      "traffic_raw": "200+",
      "traffic": 200,
      "news": {
        "title": "False Breakout",
        "source": "Moomoo",
        "url": "https://www.moomoo.com/community/feed/false-breakout-116961863663621"
      }
    },
    {
      "keyword": "레미콘",
      "traffic_raw": "200+",
      "traffic": 200,
      "news": {
        "title": "경남 남부 레미콘노조 총파업 결의대회…\"사측 단체협약 나서야\"",
        "source": "Daum",
        "url": "https://v.daum.net/v/20260722141257989"
      }
    },
    {
      "keyword": "골프",
      "traffic_raw": "200+",
      "traffic": 200,
      "news": {
        "title": "안병훈·이태훈, LIV 골프 영국 대회 첫날 공동 5위",
        "source": "연합뉴스",
        "url": "https://www.yna.co.kr/view/AKR20260724012400007"
      }
    },
    {
      "keyword": "스페이스x 주가",
      "traffic_raw": "100+",
      "traffic": 100,
      "news": {
        "title": "스페이스X 주가 반토막…\"공매도 22조원 평가익\"",
        "source": "Daum",
        "url": "https://v.daum.net/v/20260724072047544"
      }
    },
    {
      "keyword": "wti 유가",
      "traffic_raw": "100+",
      "traffic": 100,
      "news": {
        "title": "[속보]브렌트유 배럴당 100달러 돌파…5월 26일 이후 처음",
        "source": "경향신문",
        "url": "https://www.khan.co.kr/article/202607232230001"
      }
    }
  ]
}