{
  "timestamp": "2026-06-08T18:17:40.764753+09:00",
  "label": "18:17",
  "items": [
    {
      "keyword": "최혁진",
      "traffic_raw": "5000+",
      "traffic": 5000,
      "news": {
        "title": "'희대요시' 합성사진 들었던 최혁진 복당 신청에 민주당 시끌",
        "source": "Daum",
        "url": "https://v.daum.net/v/20260608155603130"
      }
    },
    {
      "keyword": "정용진",
      "traffic_raw": "2000+",
      "traffic": 2000,
      "news": {
        "title": "‘스벅 사태’ 후폭풍, 책임 경영 나서나···정용진 회장, 핵심 계열사 이마트·신세계프라퍼티 대표이사 맡는다",
        "source": "경향신문",
        "url": "https://www.khan.co.kr/article/202606081422001"
      }
    },
    {
      "keyword": "박지연",
      "traffic_raw": "2000+",
      "traffic": 2000,
      "news": {
        "title": "\"쌍욕 날리며 잘 봤습니다\" 김희철, '참교육' 박지연 역대급 빌런 연기 '극찬'",
        "source": "Daum",
        "url": "https://v.daum.net/v/20260608163722249"
      }
    },
    {
      "keyword": "국민연금공단",
      "traffic_raw": "2000+",
      "traffic": 2000,
      "news": {
        "title": "국민연금, 장애예술인 작품전 개최…\"본부가 미술관으로 변신\"",
        "source": "뉴시스",
        "url": "https://www.newsis.com/view/NISX20260608_0003660604"
      }
    },
    {
      "keyword": "신봉선",
      "traffic_raw": "1000+",
      "traffic": 1000,
      "news": {
        "title": "\"20년 전 6만원 선이었는데\"…신봉선, 안 팔고 모은 금값 '폭등'",
        "source": "뉴시스",
        "url": "https://www.newsis.com/view/NISX20260608_0003659505"
      }
    },
    {
      "keyword": "이하늘",
      "traffic_raw": "1000+",
      "traffic": 1000,
      "news": {
        "title": "[단독] \"기자들은 결국 이하늘을 쓸 것\"...재판 앞둔 이하늘, 2024년 녹취 공개",
        "source": "Daum",
        "url": "https://v.daum.net/v/20260608111658406"
      }
    },
    {
      "keyword": "삼성자산운용",
      "traffic_raw": "500+",
      "traffic": 500,
      "news": {
        "title": "'삼전·닉스' 다음은 '현대차'…피지컬AI 업고 ETF 시장 달군다",
        "source": "Daum",
        "url": "https://v.daum.net/v/20260608114335206"
      }
    },
    {
      "keyword": "한미약품",
      "traffic_raw": "200+",
      "traffic": 200,
      "news": {
        "title": "플랫폼도 후보물질도… “K바이오 상반기 기술수출 13조”",
        "source": "Daum",
        "url": "https://v.daum.net/v/20260608005315562"
      }
    },
    {
      "keyword": "현정화",
      "traffic_raw": "200+",
      "traffic": 200,
      "news": {
        "title": "'女 탁구 전설도 진땀' 현정화 감독, 하마터면 동호인에 질 뻔? 강릉세계마스터즈대회 열전",
        "source": "Daum",
        "url": "https://v.daum.net/v/QSOHBkOcIf"
      }
    },
    {
      "keyword": "푸조",
      "traffic_raw": "200+",
      "traffic": 200,
      "news": {
        "title": "[시승기] ‘1199cc 엔진 맞아?’⋯ 타보고 더 놀란 ‘푸조 하이브리드’의 정체",
        "source": "브릿지경제",
        "url": "https://www.viva100.com/article/20260607500338"
      }
    }
  ]
}