{
  "timestamp": "2026-06-23T11:12:52.882241+09:00",
  "label": "11:12",
  "items": [
    {
      "keyword": "김정은",
      "traffic_raw": "10000+",
      "traffic": 10000,
      "news": {
        "title": "김정은 \"한국 핵잠수함 추진, 한반도 정세 악화\"…핵무력 강화 강조",
        "source": "JTBC",
        "url": "https://news.jtbc.co.kr/article/NB12304564"
      }
    },
    {
      "keyword": "부부",
      "traffic_raw": "2000+",
      "traffic": 2000,
      "news": {
        "title": "월수입 1000만원 남편 \"하루하루가 기적\" 처가 반대 고백 '눈물'[결혼지옥]",
        "source": "Daum",
        "url": "https://v.daum.net/v/20260623081417819"
      }
    },
    {
      "keyword": "매일경제",
      "traffic_raw": "1000+",
      "traffic": 1000,
      "news": {
        "title": "M7 내리고 반도체 오른 뉴욕증시...심상찮은 마이크론 목표가 상향 [마켓무버의 국장 힌트]",
        "source": "Daum",
        "url": "https://v.daum.net/v/20260623074603221"
      }
    },
    {
      "keyword": "살충제",
      "traffic_raw": "200+",
      "traffic": 200,
      "news": {
        "title": "“7월부터는 모기약 못사요?”…약국가, 여름 모기철 앞두고 ‘살충제 반품 대란’",
        "source": "Daum",
        "url": "https://v.daum.net/v/20260622180300115"
      }
    },
    {
      "keyword": "황유민",
      "traffic_raw": "200+",
      "traffic": 200,
      "news": {
        "title": "강민지, 마이어 LPGA 클래식 공동 5위…우승은 야마시타(종합)",
        "source": "연합뉴스",
        "url": "https://www.yna.co.kr/view/AKR20260622002551007"
      }
    },
    {
      "keyword": "현대차",
      "traffic_raw": "200+",
      "traffic": 200,
      "news": {
        "title": "현대자동차, '현대 트랜스로컬 시리즈' 신규 참여 4개 기관 발표",
        "source": "Daum",
        "url": "https://v.daum.net/v/20260623091114652"
      }
    },
    {
      "keyword": "오연서",
      "traffic_raw": "200+",
      "traffic": 200,
      "news": {
        "title": "\"결혼? 안 하는 게 아니라 못 하는 것\" 오연서, 이상형 조건 大공개 ('아근진') [순간포착]",
        "source": "Daum",
        "url": "https://v.daum.net/v/20260623072151885"
      }
    },
    {
      "keyword": "월드컵 득점 순위",
      "traffic_raw": "100+",
      "traffic": 100,
      "news": {
        "title": "[월드컵 중간순위] G조(22일)",
        "source": "Daum",
        "url": "https://v.daum.net/v/20260622121102974"
      }
    },
    {
      "keyword": "두산베어스",
      "traffic_raw": "100+",
      "traffic": 100,
      "news": null
    },
    {
      "keyword": "예측 시장",
      "traffic_raw": "100+",
      "traffic": 100,
      "news": {
        "title": "\"韓 승리 가능성 59%\" 우승국·득점왕은?…월드컵 예측시장 7.7조 몰렸다",
        "source": "Daum",
        "url": "https://v.daum.net/v/48MOKIHlYX"
      }
    }
  ]
}