{
  "timestamp": "2026-07-05T15:30:06.799825+09:00",
  "label": "15:30",
  "items": [
    {
      "keyword": "민생회복 소비쿠폰",
      "traffic_raw": "50000+",
      "traffic": 50000,
      "news": {
        "title": "복지부, '응급이송 개선대책' 등 만든 공무원 45명 포상",
        "source": "연합뉴스",
        "url": "https://www.yna.co.kr/view/AKR20260701169800530"
      }
    },
    {
      "keyword": "두산 대 키움",
      "traffic_raw": "10000+",
      "traffic": 10000,
      "news": {
        "title": "‘SBS 인기가요’ 오늘(5일) 결방 이유는?",
        "source": "국제뉴스",
        "url": "https://www.gukjenews.com/news/articleView.html?idxno=3626601"
      }
    },
    {
      "keyword": "소진",
      "traffic_raw": "5000+",
      "traffic": 5000,
      "news": {
        "title": "'김부장' 남실장, 알고보니 걸스데이 소진 남편이었다",
        "source": "뉴시스",
        "url": "https://www.newsis.com/view/NISX20260705_0003696164"
      }
    },
    {
      "keyword": "이정효",
      "traffic_raw": "5000+",
      "traffic": 5000,
      "news": {
        "title": "'월드컵 참사' 후 첫 경기, 이정효 감독 다짐 \"수원 삼성 축구로 달래드려야 하는데... 긴장 많이 된다\" [수원 현장]",
        "source": "Daum",
        "url": "https://v.daum.net/v/20260704190518571"
      }
    },
    {
      "keyword": "전소미",
      "traffic_raw": "2000+",
      "traffic": 2000,
      "news": {
        "title": "전소미 동생 이렇게 컸어?…훌쩍 큰 에블린과 영화관 데이트 [★해시태그]",
        "source": "네이트",
        "url": "https://news.nate.com/view/20260703n15762"
      }
    },
    {
      "keyword": "린",
      "traffic_raw": "2000+",
      "traffic": 2000,
      "news": {
        "title": "이수와 이혼한 린 \"너무 친한 친구를 잃은 느낌\"",
        "source": "뉴시스",
        "url": "https://www.newsis.com/view/NISX20260705_0003696084"
      }
    },
    {
      "keyword": "영화",
      "traffic_raw": "1000+",
      "traffic": 1000,
      "news": {
        "title": "조인성, 풀 메이크업 유재석에 배신감 토로 \"나가서 세수하고 오세요\" ('뜬뜬') [순간포착]",
        "source": "Daum",
        "url": "https://v.daum.net/v/20260704221918821"
      }
    },
    {
      "keyword": "벌금",
      "traffic_raw": "500+",
      "traffic": 500,
      "news": {
        "title": "술 덜 깬 상태로 출근길 운전한 회사원 벌금 2000만원",
        "source": "경향신문",
        "url": "https://www.khan.co.kr/article/202607050851001"
      }
    },
    {
      "keyword": "박소영",
      "traffic_raw": "200+",
      "traffic": 200,
      "news": {
        "title": "박소영, 양세형과 썸 제대로 끝났다 “이상형? 박명수”(전참시)",
        "source": "Daum",
        "url": "https://v.daum.net/v/20260705060305646"
      }
    },
    {
      "keyword": "백종원",
      "traffic_raw": "200+",
      "traffic": 200,
      "news": {
        "title": "대패삼겹살 원조?…법원 “백종원 개발 아니다”",
        "source": "채널A",
        "url": "https://ichannela.com/news/detail/000000537975.do"
      }
    }
  ]
}