{
  "timestamp": "2026-05-30T23:58:57.323869+09:00",
  "label": "23:58",
  "items": [
    {
      "keyword": "하지원",
      "traffic_raw": "2000+",
      "traffic": 2000,
      "news": {
        "title": "47세 하지원, '음중' 깜짝 출격…복근 드러내고 무대 장악",
        "source": "Daum",
        "url": "https://v.daum.net/v/20260530202324709"
      }
    },
    {
      "keyword": "신입사원 강회장",
      "traffic_raw": "500+",
      "traffic": 500,
      "news": {
        "title": "손현주, 전격 은퇴 선언..거센 후폭풍[신입사원 강회장]",
        "source": "Daum",
        "url": "https://v.daum.net/v/ZXAoALcny6"
      }
    },
    {
      "keyword": "김강우",
      "traffic_raw": "200+",
      "traffic": 200,
      "news": {
        "title": "‘한혜진♥’ 기성용, 현역 은퇴 후 계획 밝혔다..“여행 다니고, 재밌게 살고파”",
        "source": "조선일보",
        "url": "https://www.chosun.com/entertainments/broadcast/2026/05/28/GVQTMMLGMU4TMNBXGYZGCZTCGY/"
      }
    },
    {
      "keyword": "lpl",
      "traffic_raw": "200+",
      "traffic": 200,
      "news": {
        "title": "LPL Financial Holdings Inc. $LPLA Holdings Decreased by Catalyst Capital Advisors LLC",
        "source": "MarketBeat",
        "url": "https://www.marketbeat.com/instant-alerts/filing-lpl-financial-holdings-inc-lpla-holdings-decreased-by-catalyst-capital-advisors-llc-2026-05-30/"
      }
    },
    {
      "keyword": "부산행",
      "traffic_raw": "200+",
      "traffic": 200,
      "news": {
        "title": "‘K-좀비’ 위력 이정도였나…‘군체’ 개봉 열흘 만에 300만 고지 안착",
        "source": "Daum",
        "url": "https://v.daum.net/v/20260530215905855"
      }
    },
    {
      "keyword": "만달로리안",
      "traffic_raw": "200+",
      "traffic": 200,
      "news": {
        "title": "존 파브로 감독 “《만달로리안과 그로구》는 새 세대를 위한 스타워즈”",
        "source": "Daum",
        "url": "https://v.daum.net/v/20260530150153303"
      }
    },
    {
      "keyword": "sbs",
      "traffic_raw": "200+",
      "traffic": 200,
      "news": {
        "title": "하정우·박민식·한동훈 선거유세 대격돌 현재 구포시장 [현장영상] [나의선택2026] / 채널A",
        "source": "채널A",
        "url": "https://ichannela.com/news/digitalspecial/detail/Ba-cd1VCi0Y.do"
      }
    },
    {
      "keyword": "페이즈",
      "traffic_raw": "200+",
      "traffic": 200,
      "news": {
        "title": "'7연승' 임재현 대행, \"케리아 궁극기 보고 놀라\"",
        "source": "Daum",
        "url": "https://v.daum.net/v/20260529115617342"
      }
    },
    {
      "keyword": "신혜선",
      "traffic_raw": "100+",
      "traffic": 100,
      "news": {
        "title": "'은밀한 감사' 신혜선♥공명, 악의적 기사로 거센 위기 - 머니투데이",
        "source": "머니투데이",
        "url": "https://www.mt.co.kr/entertainment/2026/05/30/2026053009247249394"
      }
    },
    {
      "keyword": "영화 백룸",
      "traffic_raw": "100+",
      "traffic": 100,
      "news": {
        "title": "20세 영화감독, 할리우드 흔들다… ‘백룸’ 개봉 전 상영으로 900만 달러",
        "source": "Daum",
        "url": "https://v.daum.net/v/20260530084940345"
      }
    }
  ]
}