{
  "timestamp": "2026-07-21T08:47:22.686074+09:00",
  "label": "08:47",
  "items": [
    {
      "keyword": "워렌 버핏",
      "traffic_raw": "5000+",
      "traffic": 5000,
      "news": {
        "title": "결국 깨진 20년 우정...버핏, 기부 대상에서 게이츠 재단 영구 제외",
        "source": "조선일보",
        "url": "https://www.chosun.com/international/international_general/2026/07/15/BUUQ7JFQH5ASLDJKIVJEPDCAQE/"
      }
    },
    {
      "keyword": "2030 년 fifa 월드컵",
      "traffic_raw": "1000+",
      "traffic": 1000,
      "news": {
        "title": "모로코, 2030 월드컵 앞두고 76조 투자해 숙박시설 20% 확충",
        "source": "마켓인",
        "url": "https://marketin.edaily.co.kr/News/ReadE?newsId=02610886645516816"
      }
    },
    {
      "keyword": "재산세",
      "traffic_raw": "1000+",
      "traffic": 1000,
      "news": {
        "title": "강남구, 재산세 고지서 재발송 '인쇄 한 번'으로 자동화",
        "source": "아시아경제",
        "url": "https://www.asiae.co.kr/article/2026072108032831666"
      }
    },
    {
      "keyword": "weather",
      "traffic_raw": "1000+",
      "traffic": 1000,
      "news": {
        "title": "Video New severe weather threat takes aim at Midwest and East Coast",
        "source": "ABC News - Breaking News, Latest News and Videos",
        "url": "https://abcnews.com/video/134910693/"
      }
    },
    {
      "keyword": "크리스 페덱",
      "traffic_raw": "500+",
      "traffic": 500,
      "news": {
        "title": "삼성에서 뛸 운명…‘푸른 눈의 사자’ 페덱이 우승하러 왔다",
        "source": "Daum",
        "url": "https://v.daum.net/v/x99oXRQ9TA"
      }
    },
    {
      "keyword": "아시안 게임",
      "traffic_raw": "500+",
      "traffic": 500,
      "news": {
        "title": "[오피셜] 이민성호 '日·中·베트남 피했다' 아시안게임 남자축구 '톱시드' 배정... 23일 조 추첨",
        "source": "Daum",
        "url": "https://v.daum.net/v/Wi5FROrNCg"
      }
    },
    {
      "keyword": "록히드 마틴",
      "traffic_raw": "200+",
      "traffic": 200,
      "news": {
        "title": "록히드마틴, '기존 모델 반값' 저가형 패트리엇 양산 추진",
        "source": "연합뉴스",
        "url": "https://www.yna.co.kr/view/AKR20260720172800071"
      }
    },
    {
      "keyword": "대학수학능력시험",
      "traffic_raw": "200+",
      "traffic": 200,
      "news": {
        "title": "영어 절대평가가 초래한 ‘수능 혼돈’… 개혁하려다 기형화",
        "source": "Daum",
        "url": "https://v.daum.net/v/20260721000739539"
      }
    },
    {
      "keyword": "한화솔루션",
      "traffic_raw": "100+",
      "traffic": 100,
      "news": {
        "title": "한화솔루션, 유증으로 1조1713억원 조달 확정…추가 재원 마련 과제",
        "source": "기후에너지데이터뱅크",
        "url": "https://edata.ekn.kr/article/view/ekn202607210001"
      }
    },
    {
      "keyword": "임수향",
      "traffic_raw": "100+",
      "traffic": 100,
      "news": {
        "title": "\"62평 청담 대저택·슈퍼카, '허세'\" 깨달음..임수향 \"부도 NO, 번아웃\" 고백 [남겨서 뭐하게][★밤TView]",
        "source": "Daum",
        "url": "https://v.daum.net/v/b9l22rEoS9"
      }
    }
  ]
}