{
  "timestamp": "2026-07-23T17:11:14.057732+09:00",
  "label": "17:11",
  "items": [
    {
      "keyword": "열사병",
      "traffic_raw": "2000+",
      "traffic": 2000,
      "news": {
        "title": "\"여름휴가 잡아놨는데 어쩌나\"…40도 '펄펄' 끓는 일본, 열사병 환자 폭증",
        "source": "Daum",
        "url": "https://v.daum.net/v/20260723140749211"
      }
    },
    {
      "keyword": "산불",
      "traffic_raw": "2000+",
      "traffic": 2000,
      "news": {
        "title": "“41도 폭염 끓더니 12도 ‘뚝’ 떨어졌다”…유럽 이번엔 폭우·뇌우 비상",
        "source": "Daum",
        "url": "https://v.daum.net/v/20260723135737683"
      }
    },
    {
      "keyword": "푸바오",
      "traffic_raw": "1000+",
      "traffic": 1000,
      "news": {
        "title": "생후 50일 된 에버랜드 막내 판다 '많이 컸죠?'",
        "source": "Daum",
        "url": "https://v.daum.net/v/FLgndf2uZB"
      }
    },
    {
      "keyword": "mlb",
      "traffic_raw": "1000+",
      "traffic": 1000,
      "news": {
        "title": "Boston extends 15-game win streak, ties 80-year franchise record - CHOSUNBIZ",
        "source": "Chosunbiz",
        "url": "https://biz.chosun.com/en/en-sports/2026/07/23/XCVR5KKZXJBUTJZFEYU6S5ITJM/"
      }
    },
    {
      "keyword": "보스턴 레드삭스",
      "traffic_raw": "1000+",
      "traffic": 1000,
      "news": {
        "title": "하지원, MLB ‘승리의 시구’…보스턴 80년만에 15연승",
        "source": "동아일보",
        "url": "https://www.donga.com/news/Inter/article/all/20260723/134350925/1"
      }
    },
    {
      "keyword": "인천 유나이티드 fc",
      "traffic_raw": "200+",
      "traffic": 200,
      "news": {
        "title": "[오피셜] 1분도 못 뛰고 6개월 만에 '또' 방출…정태욱, 인천과 '계약 해지'",
        "source": "네이트",
        "url": "https://sports.news.nate.com/view/20260723n22791"
      }
    },
    {
      "keyword": "윤건영",
      "traffic_raw": "200+",
      "traffic": 200,
      "news": {
        "title": "[고수다] \"유시민 썩은 비평으로 대통령 난도질\"‥\"범죄자가 서울시장 해선 안 돼\"",
        "source": "Daum",
        "url": "https://v.daum.net/v/20260723160415243"
      }
    },
    {
      "keyword": "박은빈",
      "traffic_raw": "200+",
      "traffic": 200,
      "news": {
        "title": "박은빈 맞아? 숏컷에 몰라볼 뻔…9월 팬콘서트 개최",
        "source": "Daum",
        "url": "https://v.daum.net/v/20260723091937430"
      }
    },
    {
      "keyword": "맹승지",
      "traffic_raw": "200+",
      "traffic": 200,
      "news": {
        "title": "'무도' 맹승지 맞아?…인중축소술 후 확 바뀐 얼굴",
        "source": "파이낸셜뉴스",
        "url": "https://www.fnnews.com/news/202607230847015104"
      }
    },
    {
      "keyword": "국민성장펀드",
      "traffic_raw": "100+",
      "traffic": 100,
      "news": {
        "title": "전력·용수만 필요할까? 서남권 반도체 클러스터 성공의 키는 광물…자원외교에 성패 달렸다",
        "source": "Daum",
        "url": "https://v.daum.net/v/20260723153510659"
      }
    }
  ]
}