{
  "timestamp": "2026-07-03T10:58:43.583569+09:00",
  "label": "10:58",
  "items": [
    {
      "keyword": "국민연금공단",
      "traffic_raw": "20000+",
      "traffic": 20000,
      "news": {
        "title": "“7월에 수십조 판다더니”…국민연금 ‘매도폭탄설’ 현실은 달랐다? [잇슈 머니]",
        "source": "KBS 뉴스",
        "url": "https://news.kbs.co.kr/news/view.do?ncd=8601145"
      }
    },
    {
      "keyword": "고려아연",
      "traffic_raw": "10000+",
      "traffic": 10000,
      "news": {
        "title": "고려아연 노조 \"진보당 의원과 적대적 인수 시도 중단 공동노력\"",
        "source": "연합뉴스",
        "url": "https://www.yna.co.kr/view/AKR20260703045900057"
      }
    },
    {
      "keyword": "일본",
      "traffic_raw": "10000+",
      "traffic": 10000,
      "news": {
        "title": "\"여성과 약자만 골라 '어깨빵'\"…일본인 참교육한 한국인 유튜버 '통쾌'[영상]",
        "source": "뉴스1",
        "url": "https://www.news1.kr/society/general-society/6215911"
      }
    },
    {
      "keyword": "전망대",
      "traffic_raw": "2000+",
      "traffic": 2000,
      "news": {
        "title": "[시민기자]부산 파노라마 뷰… 천마산 복합전망대 베일 벗다",
        "source": "국제신문",
        "url": "https://www.kookje.co.kr/news2011/asp/newsbody.asp?code=8800&key=20260701.99099000055"
      }
    },
    {
      "keyword": "카디널스 대 브레이브스",
      "traffic_raw": "500+",
      "traffic": 500,
      "news": {
        "title": "김하성, 결별의 시간 임박…애틀랜타, 텔레즈 방출-유격수 자비스 콜업",
        "source": "Daum",
        "url": "https://v.daum.net/v/20260703054038457"
      }
    },
    {
      "keyword": "португалия – хорватия",
      "traffic_raw": "500+",
      "traffic": 500,
      "news": {
        "title": "ФОТО. Трогательно. Роналду надел футболку Жоты и посвятил ему победу",
        "source": "Sport.ua",
        "url": "https://sport.ua/news/885848-foto-trogatelno-ronaldu-nadel-futbolku-zhoty-i-posvyatil-emu-pobedu"
      }
    },
    {
      "keyword": "โปรตุเกส พบ โครเอเชีย",
      "traffic_raw": "500+",
      "traffic": 500,
      "news": {
        "title": "ลิงก์สำหรับรับชมการถ่ายทอดสดฟุตบอลโลก 2026 วันนี้ 3 กรกฎาคม",
        "source": "Vietnam.vn",
        "url": "https://www.vietnam.vn/th/link-xem-truc-tiep-world-cup-2026-hom-nay-3-7"
      }
    },
    {
      "keyword": "키 이우",
      "traffic_raw": "500+",
      "traffic": 500,
      "news": {
        "title": "러, 키이우 대공습에 최소 27명 사망…“개전 이후 최악 공격”",
        "source": "Daum",
        "url": "https://v.daum.net/v/20260703062952477"
      }
    },
    {
      "keyword": "의정부시",
      "traffic_raw": "200+",
      "traffic": 200,
      "news": {
        "title": "의정부성모병원, 신경외과 황의현 교수...지역 어르신 대상 뇌·척추 건강강좌 개최",
        "source": "국제뉴스",
        "url": "https://www.gukjenews.com/news/articleView.html?idxno=3623883"
      }
    },
    {
      "keyword": "병역",
      "traffic_raw": "200+",
      "traffic": 200,
      "news": {
        "title": "충북지방병무청, 병무담당 현장체험 교육",
        "source": "충청매일",
        "url": "https://www.ccdn.co.kr/news/articleView.html?idxno=1086375"
      }
    }
  ]
}